{
  "texture": {
    "id": "m_chain_gloves",
    "file": "images/avatar/male/chain_gloves.png"
  },
  "texturePack": {
    "id": "m_chain_gloves",
    "texture": "m_chain_gloves",
    "invertOffsets": true,
    "absoluteOffsets": true,
    "rects": [
      { "rect": [229, 306, 33, 33], "offset": [17, 35] },
      { "rect": [241, 99, 33, 32], "offset": [17, 34] },
      { "rect": [197, 232, 34, 32], "offset": [18, 34] },
      { "rect": [274, 96, 33, 31], "offset": [17, 33] },
      { "rect": [384, 36, 21, 31], "offset": [11, 35] },
      { "rect": [444, 128, 20, 31], "offset": [11, 35] },
      { "rect": [207, 128, 22, 30], "offset": [12, 34] },
      { "rect": [429, 234, 20, 29], "offset": [11, 33] },
      { "rect": [128, 201, 34, 29], "offset": [15, 35] },
      { "rect": [208, 99, 33, 29], "offset": [15, 35] },
      { "rect": [239, 71, 33, 28], "offset": [15, 34] },
      { "rect": [407, 100, 32, 28], "offset": [15, 34] },
      { "rect": [128, 102, 36, 22], "offset": [12, 32] },
      { "rect": [128, 80, 35, 22], "offset": [11, 32] },
      { "rect": [201, 456, 36, 23], "offset": [12, 32] },
      { "rect": [46, 221, 35, 21], "offset": [12, 31] },
      { "rect": [229, 339, 33, 25], "offset": [9, 30] },
      { "rect": [265, 364, 32, 25], "offset": [8, 30] },
      { "rect": [399, 263, 32, 25], "offset": [8, 30] },
      { "rect": [207, 75, 32, 24], "offset": [8, 29] },
      { "rect": [172, 331, 20, 32], "offset": [2, 33] },
      { "rect": [431, 263, 19, 32], "offset": [1, 32] },
      { "rect": [443, 159, 20, 32], "offset": [1, 32] },
      { "rect": [378, 356, 20, 30], "offset": [1, 31] },
      { "rect": [198, 200, 33, 32], "offset": [10, 32] },
      { "rect": [450, 32, 32, 31], "offset": [10, 31] },
      { "rect": [97, 152, 31, 31], "offset": [9, 31] },
      { "rect": [170, 448, 31, 31], "offset": [9, 31] },
      { "rect": [155, 304, 37, 27], "offset": [18, 30] },
      { "rect": [192, 306, 37, 26], "offset": [18, 30] },
      { "rect": [229, 364, 36, 25], "offset": [17, 29] },
      { "rect": [408, 155, 35, 25], "offset": [16, 29] },
      { "rect": [292, 390, 31, 27], "offset": [12, 34] },
      { "rect": [281, 153, 31, 32], "offset": [12, 36] },
      { "rect": [260, 229, 27, 35], "offset": [10, 38] },
      { "rect": [287, 296, 28, 32], "offset": [10, 36] },
      { "rect": [283, 185, 29, 27], "offset": [10, 34] },
      { "rect": [231, 231, 29, 33], "offset": [10, 37] },
      { "rect": [228, 417, 28, 36], "offset": [9, 39] },
      { "rect": [289, 328, 30, 32], "offset": [11, 37] },
      { "rect": [378, 67, 29, 32], "offset": [11, 36] },
      { "rect": [349, 325, 22, 31], "offset": [6, 33] },
      { "rect": [279, 417, 19, 38], "offset": [6, 40] },
      { "rect": [439, 372, 19, 25], "offset": [4, 28] },
      { "rect": [315, 279, 23, 32], "offset": [6, 36] },
      { "rect": [338, 228, 33, 27], "offset": [12, 34] },
      { "rect": [265, 33, 40, 29], "offset": [15, 36] },
      { "rect": [408, 128, 36, 27], "offset": [14, 34] },
      { "rect": [398, 356, 19, 30], "offset": [5, 32] },
      { "rect": [172, 384, 26, 34], "offset": [9, 37] },
      { "rect": [128, 124, 36, 32], "offset": [15, 37] },
      { "rect": [97, 336, 30, 32], "offset": [12, 37] },
      { "rect": [458, 372, 19, 25], "offset": [6, 29] },
      { "rect": [262, 334, 27, 30], "offset": [9, 33] },
      { "rect": [129, 479, 35, 30], "offset": [14, 34] },
      { "rect": [311, 215, 27, 31], "offset": [10, 34] },
      { "rect": [312, 127, 26, 31], "offset": [8, 35] },
      { "rect": [338, 201, 33, 27], "offset": [13, 34] },
      { "rect": [340, 61, 38, 27], "offset": [15, 34] },
      { "rect": [237, 453, 36, 26], "offset": [14, 34] },
      { "rect": [371, 278, 28, 29], "offset": [10, 35] },
      { "rect": [397, 386, 20, 30], "offset": [5, 33] },
      { "rect": [331, 442, 19, 32], "offset": [6, 33] },
      { "rect": [377, 386, 20, 31], "offset": [4, 33] },
      { "rect": [273, 455, 31, 24], "offset": [12, 32] },
      { "rect": [97, 368, 30, 26], "offset": [11, 32] },
      { "rect": [173, 418, 28, 30], "offset": [9, 33] },
      { "rect": [371, 249, 28, 29], "offset": [9, 33] },
      { "rect": [349, 356, 29, 26], "offset": [10, 32] },
      { "rect": [348, 382, 29, 26], "offset": [11, 32] },
      { "rect": [228, 479, 29, 30], "offset": [11, 33] },
      { "rect": [261, 389, 31, 28], "offset": [12, 32] },
      { "rect": [99, 123, 29, 29], "offset": [11, 35] },
      { "rect": [335, 474, 19, 31], "offset": [6, 33] },
      { "rect": [329, 410, 19, 32], "offset": [5, 33] },
      { "rect": [416, 325, 17, 30], "offset": [6, 33] },
      { "rect": [313, 479, 22, 30], "offset": [8, 34] },
      { "rect": [338, 280, 32, 27], "offset": [13, 34] },
      { "rect": [345, 36, 39, 25], "offset": [17, 34] },
      { "rect": [372, 169, 35, 26], "offset": [15, 34] },
      { "rect": [379, 477, 16, 26], "offset": [4, 29] },
      { "rect": [297, 360, 24, 30], "offset": [8, 33] },
      { "rect": [162, 200, 36, 30], "offset": [14, 34] },
      { "rect": [198, 479, 30, 30], "offset": [11, 34] },
      { "rect": [378, 449, 17, 28], "offset": [5, 32] },
      { "rect": [287, 212, 24, 33], "offset": [9, 37] },
      { "rect": [60, 448, 35, 33], "offset": [14, 38] },
      { "rect": [311, 246, 27, 33], "offset": [10, 37] },
      { "rect": [287, 245, 24, 32], "offset": [9, 36] },
      { "rect": [374, 99, 33, 29], "offset": [12, 34] },
      { "rect": [91, 481, 38, 28], "offset": [16, 35] },
      { "rect": [372, 128, 36, 27], "offset": [15, 34] },
      { "rect": [286, 479, 27, 30], "offset": [10, 36] },
      { "rect": [464, 140, 18, 29], "offset": [6, 32] },
      { "rect": [464, 63, 18, 39], "offset": [4, 41] },
      { "rect": [417, 355, 19, 29], "offset": [7, 32] }
    ],
    "groups": [
      { "range": [0, 31], "directions": 8, "animationType": "backAndForth" },
      { "range": [32, 95], "directions": 8, "animationType": "looped" }
    ]
  }
}