{
  "texture": {
    "id": "m_slingshot",
    "file": "images/avatar/male/slingshot.png"
  },
  "texturePack": {
    "id": "m_slingshot",
    "texture": "m_slingshot",
    "invertOffsets": true,
    "absoluteOffsets": true,
    "rects": [
      { "rect": [373, 59, 15, 21], "offset": [6, 25] },
      { "rect": [252, 146, 15, 21], "offset": [6, 24] },
      { "rect": [280, 125, 15, 21], "offset": [6, 24] },
      { "rect": [223, 146, 15, 19], "offset": [6, 23] },
      { "rect": [465, 53, 6, 11], "offset": [13, 28] },
      { "rect": [465, 64, 6, 11], "offset": [13, 28] },
      { "rect": [466, 174, 6, 11], "offset": [13, 27] },
      { "rect": [472, 174, 6, 11], "offset": [13, 27] },
      { "rect": [132, 151, 13, 26], "offset": [16, 33] },
      { "rect": [169, 114, 13, 26], "offset": [16, 33] },
      { "rect": [191, 140, 13, 25], "offset": [16, 32] },
      { "rect": [242, 87, 12, 25], "offset": [16, 32] },
      { "rect": [157, 116, 12, 26], "offset": [11, 38] },
      { "rect": [375, 34, 12, 25], "offset": [11, 37] },
      { "rect": [195, 111, 12, 25], "offset": [11, 37] },
      { "rect": [254, 85, 11, 25], "offset": [11, 36] },
      { "rect": [328, 38, 13, 23], "offset": [-2, 38] },
      { "rect": [436, 54, 13, 23], "offset": [-2, 38] },
      { "rect": [295, 125, 11, 21], "offset": [-4, 36] },
      { "rect": [411, 182, 9, 6], "offset": [-6, 21] },
      { "rect": [107, 70, 15, 25], "offset": [-7, 37] },
      { "rect": [199, 61, 15, 25], "offset": [-7, 37] },
      { "rect": [147, 164, 15, 24], "offset": [-7, 36] },
      { "rect": [162, 164, 15, 24], "offset": [-7, 36] },
      { "rect": [294, 60, 14, 23], "offset": [-11, 31] },
      { "rect": [193, 165, 14, 23], "offset": [-11, 31] },
      { "rect": [207, 165, 14, 23], "offset": [-11, 31] },
      { "rect": [163, 142, 14, 22], "offset": [-11, 30] },
      { "rect": [359, 34, 16, 23], "offset": [-4, 26] },
      { "rect": [357, 57, 16, 23], "offset": [-4, 26] },
      { "rect": [387, 33, 16, 23], "offset": [-4, 26] },
      { "rect": [276, 103, 16, 22], "offset": [-4, 25] },
      { "rect": [292, 103, 14, 22], "offset": [-6, 27] },
      { "rect": [394, 80, 15, 20], "offset": [-5, 23] },
      { "rect": [419, 54, 17, 22], "offset": [-1, 25] },
      { "rect": [334, 102, 16, 22], "offset": [-2, 25] },
      { "rect": [306, 125, 15, 21], "offset": [-4, 25] },
      { "rect": [335, 146, 15, 22], "offset": [-6, 29] },
      { "rect": [283, 146, 14, 24], "offset": [-7, 34] },
      { "rect": [450, 76, 14, 22], "offset": [-7, 30] },
      { "rect": [324, 61, 18, 21], "offset": [-1, 24] },
      { "rect": [350, 102, 18, 19], "offset": [5, 21] },
      { "rect": [306, 103, 16, 22], "offset": [10, 24] },
      { "rect": [266, 167, 17, 21], "offset": [8, 24] },
      { "rect": [284, 83, 18, 20], "offset": [4, 23] },
      { "rect": [207, 107, 18, 21], "offset": [-3, 25] },
      { "rect": [277, 60, 17, 23], "offset": [-8, 29] },
      { "rect": [145, 142, 18, 22], "offset": [-5, 26] },
      { "rect": [227, 128, 19, 18], "offset": [6, 20] },
      { "rect": [403, 33, 18, 21], "offset": [13, 24] },
      { "rect": [62, 163, 16, 25], "offset": [17, 29] },
      { "rect": [322, 103, 12, 22], "offset": [15, 28] },
      { "rect": [421, 33, 18, 21], "offset": [10, 25] },
      { "rect": [207, 128, 20, 18], "offset": [3, 21] },
      { "rect": [233, 38, 20, 21], "offset": [-3, 23] },
      { "rect": [24, 169, 19, 19], "offset": [1, 21] },
      { "rect": [238, 146, 14, 19], "offset": [13, 23] },
      { "rect": [403, 54, 16, 23], "offset": [17, 29] },
      { "rect": [199, 35, 14, 26], "offset": [17, 35] },
      { "rect": [191, 86, 14, 25], "offset": [16, 33] },
      { "rect": [308, 58, 16, 24], "offset": [14, 29] },
      { "rect": [205, 86, 18, 21], "offset": [10, 23] },
      { "rect": [308, 38, 20, 20], "offset": [7, 21] },
      { "rect": [223, 87, 19, 20], "offset": [10, 21] },
      { "rect": [368, 102, 14, 19], "offset": [13, 28] },
      { "rect": [177, 140, 14, 25], "offset": [12, 35] },
      { "rect": [165, 88, 15, 26], "offset": [8, 39] },
      { "rect": [180, 88, 11, 26], "offset": [9, 38] },
      { "rect": [182, 114, 13, 26], "offset": [11, 34] },
      { "rect": [385, 159, 14, 20], "offset": [13, 28] },
      { "rect": [436, 77, 14, 22], "offset": [13, 24] },
      { "rect": [422, 140, 10, 19], "offset": [14, 26] },
      { "rect": [246, 128, 18, 18], "offset": [12, 28] },
      { "rect": [351, 82, 10, 20], "offset": [-3, 33] },
      { "rect": [142, 116, 15, 26], "offset": [-4, 40] },
      { "rect": [235, 165, 13, 23], "offset": [-4, 36] },
      { "rect": [469, 137, 10, 8], "offset": [-2, 20] },
      { "rect": [377, 80, 17, 20], "offset": [13, 31] },
      { "rect": [367, 121, 16, 20], "offset": [17, 29] },
      { "rect": [350, 141, 17, 20], "offset": [15, 30] },
      { "rect": [302, 83, 14, 20], "offset": [1, 31] },
      { "rect": [253, 38, 19, 22], "offset": [-2, 34] },
      { "rect": [244, 60, 16, 25], "offset": [-9, 36] },
      { "rect": [260, 60, 17, 23], "offset": [-6, 35] },
      { "rect": [44, 165, 18, 23], "offset": [0, 34] },
      { "rect": [257, 110, 19, 18], "offset": [9, 30] },
      { "rect": [350, 121, 17, 20], "offset": [15, 32] },
      { "rect": [265, 83, 19, 20], "offset": [11, 31] },
      { "rect": [272, 38, 18, 22], "offset": [-2, 30] },
      { "rect": [225, 107, 17, 21], "offset": [-8, 28] },
      { "rect": [388, 56, 15, 24], "offset": [-11, 30] },
      { "rect": [449, 53, 16, 23], "offset": [-9, 29] },
      { "rect": [290, 38, 18, 22], "offset": [-5, 29] },
      { "rect": [267, 146, 16, 21], "offset": [-2, 31] },
      { "rect": [399, 162, 12, 21], "offset": [-2, 33] },
      { "rect": [384, 139, 15, 20], "offset": [-2, 31] }
    ],
    "groups": [
      { "range": [0, 31], "directions": 8, "animationType": "backAndForth" },
      { "range": [32, 95], "directions": 8, "animationType": "looped" }
    ]
  }
}