{
  "variable": [
    { "colorCycleSpeed": 60 },
    { "colorCycleStart": 1 },
    { "colorCycleStop": 32 }
  ],
  "palette": [
    {
      "id": "l3_4",
      "file": "levels/l3data/l3_4.pal"
    },
    {
      "id": "colorCycle",
      "fromId": "l3_4"
    }
  ],
  "level": {
    "id": "level",
    "palette": "l3_4",
    "file": "levels/l3data/l3.cel",
    "outOfBoundsTileLayer2": 7,
    "til": "levels/l3data/l3.til",
    "min": "levels/l3data/l3.min",
    "minBlocks": 10,
    "sol": "levels/l3data/l3.sol"
  },
  "load": "level/automap/l3/load.json",
  "load": "level/l12/levelObjects.json",
  "load": "level/l12/monsters.json",
  "load": "level/l12/level2.json"
}