{
  "action": {
    "name": "if.equal",
    "param1": "%beta%",
    "param2": true,
    "then": { "name": "load", "file": "level/player/Sorceror/textureFilesBeta.json" },
    "else": { "name": "load", "file": "level/player/Sorceror/textureFiles.json" }
  },
  "load": ["level/player/loadCELTexture.json", "sha", "town", "sorcerorLeatherAxe"],
  "load": ["level/player/loadCELTexture.json", "shb", "town", "sorcerorLeatherBow"],
  "load": ["level/player/loadCELTexture.json", "shd", "town", "sorcerorLeatherShieldSword"],
  "load": ["level/player/loadCELTexture.json", "shh", "town", "sorcerorLeatherShieldClub"],
  "load": ["level/player/loadCELTexture.json", "shm", "town", "sorcerorLeatherClub"],
  "load": ["level/player/loadCELTexture.json", "shn", "town", "sorcerorLeather"],
  "load": ["level/player/loadCELTexture.json", "shs", "town", "sorcerorLeatherSword"],
  "load": ["level/player/loadCELTexture.json", "sht", "town", "sorcerorLeatherStaff"],
  "load": ["level/player/loadCELTexture.json", "shu", "town", "sorcerorLeatherShield"],
  "load": ["level/player/loadCELTexture.json", "sla", "town", "sorcerorNormalAxe"],
  "load": ["level/player/loadCELTexture.json", "slb", "town", "sorcerorNormalBow"],
  "load": ["level/player/loadCELTexture.json", "sld", "town", "sorcerorNormalShieldSword"],
  "load": ["level/player/loadCELTexture.json", "slh", "town", "sorcerorNormalShieldClub"],
  "load": ["level/player/loadCELTexture.json", "slm", "town", "sorcerorNormalClub"],
  "load": ["level/player/loadCELTexture.json", "sln", "town", "sorcerorNormal"],
  "load": ["level/player/loadCELTexture.json", "sls", "town", "sorcerorNormalSword"],
  "load": ["level/player/loadCELTexture.json", "slt", "town", "sorcerorNormalStaff"],
  "load": ["level/player/loadCELTexture.json", "slu", "town", "sorcerorNormalShield"],
  "load": ["level/player/loadCELTexture.json", "sma", "town", "sorcerorPlateAxe"],
  "load": ["level/player/loadCELTexture.json", "smb", "town", "sorcerorPlateBow"],
  "load": ["level/player/loadCELTexture.json", "smd", "town", "sorcerorPlateShieldSword"],
  "load": ["level/player/loadCELTexture.json", "smh", "town", "sorcerorPlateShieldClub"],
  "load": ["level/player/loadCELTexture.json", "smm", "town", "sorcerorPlateClub"],
  "load": ["level/player/loadCELTexture.json", "smn", "town", "sorcerorPlate"],
  "load": ["level/player/loadCELTexture.json", "sms", "town", "sorcerorPlateSword"],
  "load": ["level/player/loadCELTexture.json", "smt", "town", "sorcerorPlateStaff"],
  "load": ["level/player/loadCELTexture.json", "smu", "town", "sorcerorPlateShield"]
}