{
  "itemClass": [
    {
      "id": "amulet",
      "replaceVars": true,
      "dropTexturePack": "itemDrop",
      "dropTextureIndex": 35,
      "inventoryTexturePack": "itemIcons",
      "inventoryTextureIndex": 56,
      "name": "Amulet",
      "shortName": "Amulet",
      "type": "Amulet",
      "defaultOutline": "%outlineItem%",
      "defaultOutlineIgnore": "0x000000",
      "defaults": {
        "price": 1200,
        "magical": true,
        "durability": "max",
        "durabilityMax": "max"
      },
      "formulas": {
        "sell": "price * 0.25"
      },
      "descriptions": [
        { "index": 0, "name": "indestructible" },
        { "index": 1, "name": "magic" },
        { "index": 2, "name": "magic", "skip": 1 },
        { "index": 3, "name": "noAttributes" }
      ],
      "inventorySize": [1, 1],
      "actions": {
        "action": "pickItemInLevel",
        "levelDrop": { "name": "sound.play", "id": "flipring" },
        "inventoryDrop": { "name": "sound.play", "id": "invring" },
        "inventoryPick": "pickItemInInventory"
      },
      "prefix": "jewelleryPrefixes",
      "suffix": "jewellerySuffixes"
    }
  ]
}